tsl2561/__init__.py
tsl2561/constants.py
tsl2561/py.typed
tsl2561/tsl2561.py
tsl2561-3.4.0.dist-info/LICENSE
tsl2561-3.4.0.dist-info/METADATA
tsl2561-3.4.0.dist-info/WHEEL
tsl2561-3.4.0.dist-info/top_level.txt
tsl2561-3.4.0.dist-info/RECORD
