Metadata-Version: 2.1
Name: tsl2561
Version: 3.4.0
Summary: Driver for the TSL2561 digital luminosity (light) sensors
Home-page: https://github.com/sim0nx/tsl2561
Author: Georges Toth
Author-email: georges@trypill.org
License: BSD
Download-URL: https://github.com/sim0nx/tsl2561
Keywords: TSL2561
Platform: UNKNOWN
Classifier: Development Status :: 5 - Production/Stable
Classifier: License :: OSI Approved :: BSD License
Classifier: Intended Audience :: Developers
Classifier: Operating System :: POSIX :: Linux
Classifier: Programming Language :: Python
Classifier: Programming Language :: Python :: 3
Classifier: Programming Language :: Python :: 3 :: Only
Requires-Python: >=3.5
Requires-Dist: Adafruit-GPIO
